README.md
setup.py
sql_alchemy_db.egg-info/PKG-INFO
sql_alchemy_db.egg-info/SOURCES.txt
sql_alchemy_db.egg-info/dependency_links.txt
sql_alchemy_db.egg-info/requires.txt
sql_alchemy_db.egg-info/top_level.txt
src/__init__.py
src/column.py
src/database.py
src/table.py